impression/__init__.py
impression/admin.py
impression/apps.py
impression/backends.py
impression/exceptions.py
impression/forms.py
impression/settings.py
impression/template_engine.py
impression/tests.py
impression/urls.py
impression/widgets.py
impression/wsgi.py
impression/admin_ui/__init__.py
impression/admin_ui/apps.py
impression/admin_ui/sites.py
impression/api/__init__.py
impression/api/urls.py
impression/api/views.py
impression/management/__init__.py
impression/management/commands/__init__.py
impression/management/commands/impression_send_emails.py
impression/migrations/0001_initial.py
impression/migrations/__init__.py
impression/models/__init__.py
impression/models/distribution.py
impression/models/email_address.py
impression/models/message.py
impression/models/rate_limit.py
impression/models/service.py
impression/models/template.py
django_impression-0.5.0.dist-info/LICENSE
django_impression-0.5.0.dist-info/METADATA
django_impression-0.5.0.dist-info/WHEEL
django_impression-0.5.0.dist-info/top_level.txt
django_impression-0.5.0.dist-info/RECORD
