Metadata-Version: 2.1
Name: django-impression
Version: 0.5.0
Summary: CMS for email; admin UI, API, and permissions for email templates.
Home-page: https://github.com/gregschmit/django-impression
Author: Gregory N. Schmit
Author-email: schmitgreg@gmail.com
License: MIT
Platform: UNKNOWN
Classifier: Environment :: Web Environment
Classifier: Framework :: Django
Classifier: Framework :: Django :: 2.0
Classifier: Framework :: Django :: 2.1
Classifier: Framework :: Django :: 2.2
Classifier: Framework :: Django :: 3.0
Classifier: Intended Audience :: Developers
Classifier: License :: OSI Approved :: MIT License
Classifier: Programming Language :: Python :: 3
Requires-Dist: Django (>=2)
Requires-Dist: djangorestframework (>=3)
Requires-Dist: django-impression-client
Requires-Dist: beautifulsoup4 (>=4.4)
